AUTHORS.md
CHANGES.md
LICENSE
MANIFEST.in
README.rst
setup.py
gc_kafka_python.egg-info/PKG-INFO
gc_kafka_python.egg-info/SOURCES.txt
gc_kafka_python.egg-info/dependency_links.txt
gc_kafka_python.egg-info/requires.txt
gc_kafka_python.egg-info/top_level.txt
kafka/__init__.py
kafka/client.py
kafka/client_async.py
kafka/cluster.py
kafka/codec.py
kafka/common.py
kafka/conn.py
kafka/context.py
kafka/future.py
kafka/util.py
kafka/version.py
kafka/consumer/__init__.py
kafka/consumer/base.py
kafka/consumer/fetcher.py
kafka/consumer/group.py
kafka/consumer/multiprocess.py
kafka/consumer/simple.py
kafka/consumer/subscription_state.py
kafka/coordinator/__init__.py
kafka/coordinator/base.py
kafka/coordinator/consumer.py
kafka/coordinator/heartbeat.py
kafka/coordinator/protocol.py
kafka/coordinator/assignors/__init__.py
kafka/coordinator/assignors/abstract.py
kafka/coordinator/assignors/roundrobin.py
kafka/partitioner/__init__.py
kafka/partitioner/base.py
kafka/partitioner/hashed.py
kafka/partitioner/roundrobin.py
kafka/producer/__init__.py
kafka/producer/base.py
kafka/producer/keyed.py
kafka/producer/simple.py
kafka/protocol/__init__.py
kafka/protocol/abstract.py
kafka/protocol/admin.py
kafka/protocol/api.py
kafka/protocol/commit.py
kafka/protocol/fetch.py
kafka/protocol/group.py
kafka/protocol/legacy.py
kafka/protocol/message.py
kafka/protocol/metadata.py
kafka/protocol/offset.py
kafka/protocol/pickle.py
kafka/protocol/produce.py
kafka/protocol/struct.py
kafka/protocol/types.py
test/test_client.py
test/test_client_async.py
test/test_client_integration.py
test/test_codec.py
test/test_conn.py
test/test_consumer.py
test/test_consumer_group.py
test/test_consumer_integration.py
test/test_context.py
test/test_coordinator.py
test/test_failover_integration.py
test/test_package.py
test/test_partitioner.py
test/test_producer.py
test/test_producer_integration.py
test/test_protocol.py
test/test_util.py
test/testutil.py