Metadata-Version: 1.1
Name: gc-kafka-python
Version: 0.9.7
Summary: Pure Python client for Apache Kafka
Home-page: https://github.com/dpkp/kafka-python
Author: Dana Powers
Author-email: dana.powers@gmail.com
License: Apache License 2.0
Keywords: apache kafka
Platform: UNKNOWN
Classifier: Development Status :: 4 - Beta
Classifier: Intended Audience :: Developers
Classifier: License :: OSI Approved :: Apache Software License
Classifier: Programming Language :: Python
Classifier: Programming Language :: Python :: 2
Classifier: Programming Language :: Python :: 2.6
Classifier: Programming Language :: Python :: 2.7
Classifier: Programming Language :: Python :: 3
Classifier: Programming Language :: Python :: 3.3
Classifier: Programming Language :: Python :: 3.4
Classifier: Programming Language :: Python :: 3.5
Classifier: Programming Language :: Python :: Implementation :: PyPy
Classifier: Topic :: Software Development :: Libraries :: Python Modules
